{"ID":21220,"Name":"Mother of Learning"}
{"ID":63759,"Name":"Super Supportive"}
{"ID":36735,"Name":"The Perfect Run"}
{"ID":21410,"Name":"Super Minion"}
{"ID":65629,"Name":"The Game at Carousel: A Horror Movie LitRPG"}
{"ID":62125,"Name":"Ghost in the City: Cyberpunk Gamer SI"}
{"ID":92144,"Name":"The Legend of William Oh"}
{"ID":48402,"Name":"Magical Girl Gunslinger"}
{"ID":98391,"Name":"Wander West, In Shadow [Slow Burn Dark Fantasy]"}
{"ID":92820,"Name":"Phantom Star"}
{"ID":65058,"Name":"Pale Lights"}
{"ID":26675,"Name":"A Journey of Black and Red"}
{"ID":73112,"Name":"Cultist of Cerebon - Litrpg/Isekai"}
{"ID":39408,"Name":"Beware Of Chicken"}
{"ID":72498,"Name":"Sublight Drive (Star Wars)"}
{"ID":46901,"Name":"The Last Orellen"}
{"ID":75175,"Name":"Soul Guardian (cozy, comedy, slice of life) Stubbing Jan 26th"}
{"ID":43318,"Name":"The Butcher of Gadobhra"}
{"ID":71045,"Name":"Zenith of Sorcery"}
{"ID":76677,"Name":"BOC Alternate Universe: Soaring Heaven's Isle"}
{"ID":47982,"Name":"Tunnel Rat: Causing Trouble in Two Worlds"}
{"ID":75345,"Name":"Changeling"}
{"ID":69480,"Name":"The Land of Broken Roads"}
{"ID":94398,"Name":"Matabar "}
{"ID":57741,"Name":"Pokemon Trainer Vicky (Pokemon SI)"}
{"ID":44132,"Name":"The Calamitous Bob"}
{"ID":79173,"Name":"Downtown Druid"}
{"ID":97554,"Name":"Guild Mage: Apprentice [Slow Burn Epic Fantasy]"}
{"ID":97850,"Name":"Duskbound: a Monster Hunter LitRPG"}
{"ID":55418,"Name":"Rock falls, everyone dies"}
{"ID":88011,"Name":"The Four Treasures Saga [Isekai / LitRPG]"}
{"ID":73475,"Name":"Chasing Sunlight"}
{"ID":70234,"Name":"Blood \u0026 Fur"}
{"ID":34009,"Name":"A Practical Guide to Sorcery"}
{"ID":90494,"Name":"Gunsoul"}
{"ID":81046,"Name":"The Ballad Of A Semi-Benevolent Dragon"}
{"ID":38085,"Name":"Just Deserts: Revised Edition (MHA, OC)"}
{"ID":21322,"Name":"RE: Trailer Trash"}
{"ID":69298,"Name":"MEOW: Magical Emporium of Wares - A Cozy Slice-of-Life Fantasy"}
{"ID":60925,"Name":"A Nerubian's Journey"}
{"ID":83315,"Name":"Systema Delenda Est"}
{"ID":34710,"Name":"The Essence of Cultivation"}
{"ID":92374,"Name":"Hohenfels"}
{"ID":77972,"Name":"Syl [A Slime Monster Evolution LitRPG]"}
{"ID":102618,"Name":"Foxfire, Esq."}
{"ID":81002,"Name":"The Years of Apocalypse - A Time Loop Progression Fantasy"}
{"ID":15935,"Name":"There is no Epic Loot here, Only Puns."}
{"ID":36780,"Name":"Regis and Charlotte"}
{"ID":26534,"Name":"Vainqueur the Dragon"}
{"ID":42367,"Name":"12 Miles Below"}
{"ID":36950,"Name":"Borne of Caution "}
{"ID":54237,"Name":"Nowhere Stars"}
{"ID":58243,"Name":"A Soldier's Life"}
{"ID":94966,"Name":"Runeblade: A Delving LitRPG Survival Adventure [Runic Magic \u0026 Skill Merging]"}
{"ID":82591,"Name":"Magic Murder Cube Marine"}
{"ID":41330,"Name":"Virtuous Sons: A Greco Roman Xianxia"}
